core/__init__.py
core/asgi.py
core/settings.py
core/urls.py
core/wsgi.py
dynamo_blogger/__init__.py
dynamo_blogger/admin.py
dynamo_blogger/apps.py
dynamo_blogger/models.py
dynamo_blogger/tests.py
dynamo_blogger/urls.py
dynamo_blogger/views.py
dynamo_blogger/helpers/__init__.py
dynamo_blogger/helpers/timestamps.py
dynamo_blogger/migrations/0001_initial.py
dynamo_blogger/migrations/0002_alter_category_slug.py
dynamo_blogger/migrations/0003_newsletter.py
dynamo_blogger/migrations/__init__.py
dynamo_blogger/templates/base.html
dynamo_blogger/templates/blog/blog-post.html
dynamo_blogger/templates/blog/category.html
dynamo_blogger/templates/blog/index.html
dynamo_blogger-1.0.dist-info/LICENSE.txt
dynamo_blogger-1.0.dist-info/METADATA
dynamo_blogger-1.0.dist-info/WHEEL
dynamo_blogger-1.0.dist-info/top_level.txt
dynamo_blogger-1.0.dist-info/RECORD
